setup.py
bin/skid
skid/__init__.py
skid/__main__.py
skid/add.py
skid/completion.py
skid/config.py
skid/index.py
skid.egg-info/PKG-INFO
skid.egg-info/SOURCES.txt
skid.egg-info/dependency_links.txt
skid.egg-info/requires.txt
skid.egg-info/top_level.txt
skid/pdfhacks/__init__.py
skid/pdfhacks/bib.py
skid/pdfhacks/conversion.py
skid/pdfhacks/features.py
skid/pdfhacks/learn.py
skid/pdfhacks/metadata.py
skid/pdfhacks/pdfmill.py
skid/pdfhacks/skid-data.py
skid/utils/__init__.py
skid/utils/authors.py
skid/utils/bibkeys.py
skid/utils/data.py
skid/utils/delicious.py
skid/utils/fix.py
skid/utils/gscholar.py
skid/utils/gscholar1.py
skid/utils/misc.py
skid/utils/patch-date-added.py
skid/utils/scholarly.py
skid/utils/tkautocomplete.py