Metadata-Version: 1.0
Name: skid
Version: 1.0
Summary: Skid: bookmarks, simply kept in directories
Home-page: https://github.com/timvieira/skid/
Author: UNKNOWN
Author-email: UNKNOWN
License: UNKNOWN
Platform: UNKNOWN
